eval_ellipsis
