Metadata-Version: 1.0
Name: eval-ellipsis
Version: 0.1
Summary: Evaluating global level Ellipsis to useful code.
Home-page: UNKNOWN
Author: LDmitriy7
Author-email: ldm.work2019@gmail.com
License: MIT
Platform: UNKNOWN
